lazr.restfulclient-0.14.6-py3.10-nspkg.pth
lazr/restfulclient/__init__.py
lazr/restfulclient/_browser.py
lazr/restfulclient/_json.py
lazr/restfulclient/errors.py
lazr/restfulclient/resource.py
lazr/restfulclient/authorize/__init__.py
lazr/restfulclient/authorize/oauth.py
lazr/restfulclient/docs/CONTRIBUTING.rst
lazr/restfulclient/docs/Makefile
lazr/restfulclient/docs/NEWS.rst
lazr/restfulclient/docs/authorizer.standalone.rst
lazr/restfulclient/docs/caching.rst
lazr/restfulclient/docs/collections.rst
lazr/restfulclient/docs/entries.rst
lazr/restfulclient/docs/hosted-files.rst
lazr/restfulclient/docs/index.rst
lazr/restfulclient/docs/operations.rst
lazr/restfulclient/docs/retry.standalone.rst
lazr/restfulclient/docs/toplevel.rst
lazr/restfulclient/tests/__init__.py
lazr/restfulclient/tests/example.py
lazr/restfulclient/tests/test_atomicfilecache.py
lazr/restfulclient/tests/test_docs.py
lazr/restfulclient/tests/test_error.py
lazr/restfulclient/tests/test_oauth.py
lazr.restfulclient-0.14.6.dist-info/COPYING.txt
lazr.restfulclient-0.14.6.dist-info/METADATA
lazr.restfulclient-0.14.6.dist-info/WHEEL
lazr.restfulclient-0.14.6.dist-info/namespace_packages.txt
lazr.restfulclient-0.14.6.dist-info/top_level.txt
lazr.restfulclient-0.14.6.dist-info/RECORD
