Metadata-Version: 2.1
Name: lazr.restfulclient
Version: 0.14.6
Summary: A programmable client library that takes advantage of the commonalities among
Home-page: https://launchpad.net/lazr.restfulclient
Download-URL: https://launchpad.net/lazr.restfulclient/+download
Maintainer: LAZR Developers
Maintainer-email: lazr-developers@lists.launchpad.net
License: LGPL v3
Project-URL: Source, https://code.launchpad.net/lazr.restfulclient
Project-URL: Issue Tracker, https://bugs.launchpad.net/lazr.restfulclient
Project-URL: Documentation, https://lazrrestfulclient.readthedocs.io/en/latest/
Classifier: Development Status :: 5 - Production/Stable
Classifier: Intended Audience :: Developers
Classifier: License :: OSI Approved :: GNU Library or Lesser General Public License (LGPL)
Classifier: Operating System :: OS Independent
Classifier: Programming Language :: Python
Classifier: Programming Language :: Python :: 2
Classifier: Programming Language :: Python :: 3
License-File: COPYING.txt
Requires-Dist: distro
Requires-Dist: httplib2; python_version < "3"
Requires-Dist: httplib2>=0.7.7; python_version >= "3"
Requires-Dist: importlib-metadata; python_version < "3.8"
Requires-Dist: oauthlib
Requires-Dist: setuptools
Requires-Dist: six
Requires-Dist: wadllib>=1.1.4
Provides-Extra: docs
Requires-Dist: Sphinx; extra == "docs"
Provides-Extra: test
Requires-Dist: fixtures>=1.3.0; extra == "test"
Requires-Dist: lazr.authentication; extra == "test"
Requires-Dist: lazr.restful>=0.11.0; extra == "test"
Requires-Dist: mock; python_version < "3" and extra == "test"
Requires-Dist: oauth; extra == "test"
Requires-Dist: testtools; extra == "test"
Requires-Dist: wsgi_intercept; extra == "test"
Requires-Dist: zope.testrunner; extra == "test"
